gis_metadata/__init__.py
gis_metadata/arcgis_metadata_parser.py
gis_metadata/exceptions.py
gis_metadata/fgdc_metadata_parser.py
gis_metadata/iso_metadata_parser.py
gis_metadata/metadata_parser.py
gis_metadata/tests/__init__.py
gis_metadata/tests/data/arcgis_metadata.xml
gis_metadata/tests/data/fgdc_metadata.xml
gis_metadata/tests/data/iso_citation_href.xml
gis_metadata/tests/data/iso_citation_linkage.xml
gis_metadata/tests/data/iso_metadata.xml
gis_metadata/tests/data/utility_metadata.xml
gis_metadata/tests/tests.py
gis_metadata/utils.py
gis_metadata_parser-2.0.1.dist-info/LICENSE
gis_metadata_parser-2.0.1.dist-info/WHEEL
gis_metadata_parser-2.0.1.dist-info/METADATA
gis_metadata_parser-2.0.1.dist-info/RECORD
