Metadata-Version: 2.1
Name: gis-metadata-parser
Version: 2.0.1
Summary: Parser for GIS metadata standards including ArcGIS, FGDC and ISO-19115
Home-page: https://github.com/consbio/gis-metadata-parser/
License: BSD
Keywords: arcgis,fgdc,iso,ISO-19115,ISO-19139,gis,metadata,parser,xml,gis_metadata,gis_metadata_parser
Author: dharvey-consbio
Author-email: dani.harvey@consbio.org
Requires-Python: >=3.6,<4.0
Classifier: License :: Other/Proprietary License
Classifier: Programming Language :: Python :: 3
Classifier: Programming Language :: Python :: 3.6
Classifier: Programming Language :: Python :: 3.7
Classifier: Programming Language :: Python :: 3.8
Classifier: Programming Language :: Python :: 3.9
Requires-Dist: frozendict (>=2.0,<3.0)
Requires-Dist: parserutils (>=2.0.1,<3.0.0)
Project-URL: Repository, https://github.com/consbio/gis-metadata-parser/
